{
  "motto": [
    {
      "text": "Wissen.",
      "size": "medium",
      "color": "primary"
    },
    {
      "text": "Schafft.",
      "size": "medium",
      "color": "tertiary"
    },
    {
      "text": "Spass!",
      "size": "big",
      "color": "secondary"
    }
  ],
  "path": "mitmachen/elektronik",
  "title": "Mitmachen/Elektronik",
  "thumbnailUrls": [
    "images/uploads/pexels-jã©shoots-4316-technik.jpg"
  ],
  "breadcrumbs": [
    "Mitmachen/Elektronik"
  ],
  "pageSections": [
    {
      "type": "columnSection",
      "header": {
        "mainHeader": "Elektronik",
        "subHeader": "Wir haben viele elektronische Bauteile, Sensoren, Mikrocontroller, Raspberry Pis und auch viele ausgediente elektronische Geräte, aus denen du für dein Projekt wählen kannst. Mehrere Lötstationen stehen dir zur Verfügung. ",
        "divider": true,
        "sectionId": "Elektronik"
      },
      "numberColumns": 2,
      "columns": [
        {
          "type": "image",
          "width": 1,
          "imageUrl": "images/uploads/mys_material_hliebel-31-.jpg",
          "altText": "Breadboard"
        },
        {
          "type": "image",
          "width": 1,
          "imageUrl": "images/uploads/mys_material_hliebel-14-.jpg",
          "altText": "Calliope mini"
        },
        {
          "type": "paragraph",
          "width": 2,
          "text": "Egal ob du einen einfachen Schaltkreis oder eine komplizierte Schaltung machen möchtest, bei uns findest du den richtigen Ansprechpartner. Und wenn wir nicht weiter wissen, sind wir gerne bereit uns zusammen mit dir schlau zu machen."
        }
      ]
    }
  ]
}